taurex_emcee/__init__.py
taurex_emcee/autoemcee.py
taurex_emcee/emcee_optimizer.py
taurex_emcee-0.4.0rc1.dist-info/LICENSE
taurex_emcee-0.4.0rc1.dist-info/METADATA
taurex_emcee-0.4.0rc1.dist-info/WHEEL
taurex_emcee-0.4.0rc1.dist-info/entry_points.txt
taurex_emcee-0.4.0rc1.dist-info/top_level.txt
taurex_emcee-0.4.0rc1.dist-info/zip-safe
taurex_emcee-0.4.0rc1.dist-info/RECORD
