Metadata-Version: 2.1
Name: taurex_emcee
Version: 0.4.0rc1
Summary: taurex-emcee is a plugin for the TauREx 3.1 package that enables automated, parallelized atmospheric retrievals with the emcee sampler.
Author: Andrea Bocchieri <andrea.bocchieri@uniroma1.it>, Quentin Changeat, Lorenzo V. Mugnai, Enzo Pascale
License: BSD 3-Clause
Project-URL: Homepage, https://github.com/ExObsSim/taurex-emcee
Project-URL: Bug Tracker, https://github.com/ExObsSim/taurex-emcee/issues
Project-URL: Source Code, https://github.com/ExObsSim/taurex-emcee
Classifier: Development Status :: 5 - Production/Stable
Classifier: Environment :: Console
Classifier: Intended Audience :: Developers
Classifier: Intended Audience :: Science/Research
Classifier: License :: OSI Approved :: BSD License
Classifier: Operating System :: POSIX
Classifier: Operating System :: POSIX :: Linux
Classifier: Operating System :: Unix
Classifier: Operating System :: OS Independent
Classifier: Programming Language :: Python :: 3
Classifier: Topic :: Scientific/Engineering
Classifier: Topic :: Software Development :: Libraries
Requires-Python: >3.8
License-File: LICENSE
Requires-Dist: taurex
Requires-Dist: emcee
Requires-Dist: corner
Requires-Dist: arviz
Provides-Extra: docs
Requires-Dist: sphinx ~=5.0 ; extra == 'docs'
Requires-Dist: sphinxcontrib-napoleon ; extra == 'docs'
Requires-Dist: sphinxcontrib-jsmath ; extra == 'docs'
Requires-Dist: nbsphinx ~=0.9.3 ; extra == 'docs'
Requires-Dist: sphinx-rtd-theme ~=1.0.0 ; extra == 'docs'
